multidecoder/__init__.py
multidecoder/__main__.py
multidecoder/_version.py
multidecoder/domains.py
multidecoder/hit.py
multidecoder/json_conversion.py
multidecoder/keyword.py
multidecoder/keywords_to_review.txt
multidecoder/multidecoder.py
multidecoder/node.py
multidecoder/py.typed
multidecoder/query.py
multidecoder/registry.py
multidecoder/string_helper.py
multidecoder/xor_helper.py
multidecoder/xortool.py
multidecoder/decoders/__init__.py
multidecoder/decoders/base64.py
multidecoder/decoders/chr.py
multidecoder/decoders/codec.py
multidecoder/decoders/concat.py
multidecoder/decoders/filename.py
multidecoder/decoders/hex.py
multidecoder/decoders/javascript.py
multidecoder/decoders/network.py
multidecoder/decoders/path.py
multidecoder/decoders/pe_file.py
multidecoder/decoders/powershell.py
multidecoder/decoders/replace.py
multidecoder/decoders/reverse.py
multidecoder/decoders/shell.py
multidecoder/decoders/vba.py
multidecoder/decoders/xml.py
multidecoder/keywords/archive
multidecoder/keywords/av.name
multidecoder/keywords/cryptography
multidecoder/keywords/debugger.device.name
multidecoder/keywords/enable_content
multidecoder/keywords/environment.windows
multidecoder/keywords/event
multidecoder/keywords/guid
multidecoder/keywords/key
multidecoder/keywords/network.protocol
multidecoder/keywords/network.string
multidecoder/keywords/oid
multidecoder/keywords/os_name
multidecoder/keywords/powershell.cmdlet
multidecoder/keywords/privilege
multidecoder/keywords/ransomware.string
multidecoder/keywords/sandbox.id
multidecoder/keywords/security_identifier
multidecoder/keywords/user_agent
multidecoder/keywords/vba.name
multidecoder/keywords/windows.registry
multidecoder/keywords/api/api.advapi32
multidecoder/keywords/api/api.apphelp
multidecoder/keywords/api/api.atl
multidecoder/keywords/api/api.atl80
multidecoder/keywords/api/api.atl90
multidecoder/keywords/api/api.au3zip
multidecoder/keywords/api/api.avicap32
multidecoder/keywords/api/api.cabinet
multidecoder-1.6.24.dist-info/licenses/LICENSE.md
multidecoder-1.6.24.dist-info/METADATA
multidecoder-1.6.24.dist-info/WHEEL
multidecoder-1.6.24.dist-info/entry_points.txt
multidecoder-1.6.24.dist-info/top_level.txt
multidecoder-1.6.24.dist-info/RECORD
