Metadata-Version: 2.4
Name: multidecoder
Version: 1.6.24
Summary: A context preserving IOC extraction library
Home-page: https://github.com/CybercentreCanada/Multidecoder
Author: CCCS Assemblyline development team
Author-email: assemblyline@cyber.gc.ca
License: MIT
Project-URL: Bug Tracker, https://github.com/CybercentreCanada/Multidecoder/issues
Keywords: malware,analysis,gc,canada,cse-cst,cse,cst,cyber,cccs
Classifier: Programming Language :: Python :: 3
Classifier: License :: OSI Approved :: MIT License
Classifier: Operating System :: OS Independent
Requires-Python: >=3.10
License-File: LICENSE.md
Requires-Dist: pefile
Requires-Dist: regex
Dynamic: license-file
